json_to_csv_filter/__init__.py
json_to_csv_filter/json_to_csv.py
json_to_csv_filter-1.4.1.dist-info/METADATA
json_to_csv_filter-1.4.1.dist-info/WHEEL
json_to_csv_filter-1.4.1.dist-info/entry_points.txt
json_to_csv_filter-1.4.1.dist-info/licenses/LICENSE
json_to_csv_filter-1.4.1.dist-info/RECORD
